Spruce_introspect-0.1.3-py2.7-nspkg.pth
spruce/introspect/_exc.py
spruce/introspect/_modules.py
spruce/introspect/_attrs.py
spruce/introspect/_objects.py
spruce/introspect/_imp.py
spruce/introspect/_paths.py
spruce/introspect/__init__.py
Spruce_introspect-0.1.3.dist-info/top_level.txt
Spruce_introspect-0.1.3.dist-info/RECORD
Spruce_introspect-0.1.3.dist-info/pydist.json
Spruce_introspect-0.1.3.dist-info/WHEEL
Spruce_introspect-0.1.3.dist-info/namespace_packages.txt
Spruce_introspect-0.1.3.dist-info/METADATA
Spruce_introspect-0.1.3.dist-info/entry_points.txt
Spruce_introspect-0.1.3.dist-info/DESCRIPTION.rst
