Metadata-Version: 2.0
Name: Spruce-introspect
Version: 0.1.3
Summary: Inspection of Python objects and code
Home-page: UNKNOWN
Author: Ivan D Vasin
Author-email: nisavid@gmail.com
License: GNU LESSER GENERAL PUBLIC LICENSE
Requires-Dist: spruce-pprint
